.
LICENSE.txt
MANIFEST.in
README.rst
setup.cfg
setup.py
automation_rest_server/__init__.py
automation_rest_server/run.py
automation_rest_server.egg-info/PKG-INFO
automation_rest_server.egg-info/SOURCES.txt
automation_rest_server.egg-info/dependency_links.txt
automation_rest_server.egg-info/entry_points.txt
automation_rest_server.egg-info/requires.txt
automation_rest_server.egg-info/setup.py
automation_rest_server.egg-info/top_level.txt
automation_rest_server/configuration/__init__.py
automation_rest_server/configuration/config.yaml
automation_rest_server/configuration/firmware_build.yaml
automation_rest_server/configuration/pci.ids
automation_rest_server/configuration/version.yaml
automation_rest_server/configuration/web_server.yaml
automation_rest_server/rest_client/__init__.py
automation_rest_server/rest_client/web_rest_client.py
automation_rest_server/rest_client/resource/__init__.py
automation_rest_server/rest_client/resource/node_resource.py
automation_rest_server/rest_client/resource/test_resource.py
automation_rest_server/rest_client/resource/web_resource.py
automation_rest_server/rest_client/resource/models/__init__.py
automation_rest_server/rest_client/resource/models/helper.py
automation_rest_server/rest_server/__init__.py
automation_rest_server/rest_server/reset_server.py
automation_rest_server/rest_server/resource/__init__.py
automation_rest_server/rest_server/resource/benchmark_resource.py
automation_rest_server/rest_server/resource/build_firmware_resource.py
automation_rest_server/rest_server/resource/git_resource.py
automation_rest_server/rest_server/resource/iometer_benchmark_resource.py
automation_rest_server/rest_server/resource/oakgate_resource.py
automation_rest_server/rest_server/resource/operation_resource.py
automation_rest_server/rest_server/resource/state_resource.py
automation_rest_server/rest_server/resource/stop_flag_resource.py
automation_rest_server/rest_server/resource/test_resource.py
automation_rest_server/rest_server/resource/upgrade_resource.py
automation_rest_server/rest_server/resource/models/__init__.py
automation_rest_server/rest_server/resource/models/ftp_server.py
automation_rest_server/rest_server/resource/models/helper.py
automation_rest_server/test_framework/__init__.py
automation_rest_server/test_framework/database.py
