Metadata-Version: 1.1
Name: automation-rest-server
Version: 3.9.4
Summary: NVMe production server
Home-page: https://pypi.org/project/automation_rest_server
Author: yuwen123441
Author-email: yuwen123441@126.com
License: MIT License
Keywords: runner,server
Platform: any
Classifier: Development Status :: 3 - Alpha
Classifier: Intended Audience :: Developers
Classifier: Topic :: Software Development :: Libraries
Classifier: License :: OSI Approved :: MIT License
Classifier: Programming Language :: Python :: 3.6
